volvo_connected/__init__.py
volvo_connected/authentication/__init__.py
volvo_connected/authentication/dynamic_access_token_provider.py
volvo_connected/authentication/static_access_token_provider.py
volvo_connected/authentication/volvo_authentication_provider.py
volvo_connected/vcclient/kiota-lock.json
volvo_connected/vcclient/volvo_connected_client.py
volvo_connected/vcclient/models/brake_status.py
volvo_connected/vcclient/models/brake_status_data.py
volvo_connected/vcclient/models/command_accessibility.py
volvo_connected/vcclient/models/command_accessibility_data.py
volvo_connected/vcclient/models/command_list_item.py
volvo_connected/vcclient/models/command_list_item_command.py
volvo_connected/vcclient/models/command_list_response.py
volvo_connected/vcclient/models/descriptions.py
volvo_connected/vcclient/models/diagnostics.py
volvo_connected/vcclient/models/diagnostics_data.py
volvo_connected/vcclient/models/doors.py
volvo_connected/vcclient/models/doors_data.py
volvo_connected/vcclient/models/engine_diagnostics.py
volvo_connected/vcclient/models/engine_diagnostics_data.py
volvo_connected/vcclient/models/engine_start_request.py
volvo_connected/vcclient/models/engine_status.py
volvo_connected/vcclient/models/engine_status_data.py
volvo_connected/vcclient/models/error.py
volvo_connected/vcclient/models/error_response.py
volvo_connected/vcclient/models/exterior_warning.py
volvo_connected/vcclient/models/exterior_warning_data.py
volvo_connected/vcclient/models/fuel_amount.py
volvo_connected/vcclient/models/fuel_amount_data.py
volvo_connected/vcclient/models/images.py
volvo_connected/vcclient/models/invoke.py
volvo_connected/vcclient/models/invoke_data.py
volvo_connected/vcclient/models/invoke_data_invoke_status.py
volvo_connected/vcclient/models/invoke_unlock.py
volvo_connected/vcclient/models/invoke_unlock_data.py
volvo_connected/vcclient/models/invoke_unlock_data_invoke_status.py
volvo_connected/vcclient/models/odometer_value.py
volvo_connected-0.2.0.dist-info/AUTHORS.rst
volvo_connected-0.2.0.dist-info/LICENSE
volvo_connected-0.2.0.dist-info/METADATA
volvo_connected-0.2.0.dist-info/WHEEL
volvo_connected-0.2.0.dist-info/top_level.txt
volvo_connected-0.2.0.dist-info/RECORD
