Metadata-Version: 2.2
Name: volvo-connected
Version: 0.2.0
Summary: A Python package for interacting with Volvo Connect API.
Author-email: Stephan van Rooij <github@svrooij.io>
License: The MIT License (MIT)
Project-URL: Homepage, https://github.com/svrooij/py_volvo_connected/
Project-URL: Documentation, https://github.com/svrooij/py_volvo_connected/
Project-URL: Source, https://github.com/svrooij/py_volvo_connected/
Project-URL: Tracker, https://github.com/svrooij/py_volvo_connected/issues
Platform: any
Classifier: Development Status :: 4 - Beta
Classifier: Intended Audience :: Developers
Classifier: License :: OSI Approved :: MIT License
Classifier: Programming Language :: Python :: 3
Classifier: Programming Language :: Python :: 3.9
Classifier: Programming Language :: Python :: 3.10
Classifier: Programming Language :: Python :: 3.11
Classifier: Programming Language :: Python :: 3.12
Classifier: Programming Language :: Python :: 3.13
Classifier: Programming Language :: Python :: Implementation :: CPython
Classifier: Programming Language :: Python :: Implementation :: PyPy
Classifier: Operating System :: OS Independent
Classifier: Topic :: Software Development :: Libraries :: Python Modules
Classifier: Typing :: Typed
License-File: LICENSE
License-File: AUTHORS.rst
Requires-Dist: microsoft-kiota-http>=1.9.1
Requires-Dist: microsoft-kiota-serialization-json>=1.9.1
Provides-Extra: dev
Requires-Dist: black; extra == "dev"
Requires-Dist: flake8; extra == "dev"
Requires-Dist: isort; extra == "dev"
Requires-Dist: mypy; extra == "dev"
Requires-Dist: pytest; extra == "dev"
Requires-Dist: pytest-cov; extra == "dev"
Requires-Dist: pytest-mock; extra == "dev"
Requires-Dist: pytest-asyncio; extra == "dev"
Requires-Dist: requests-mock; extra == "dev"
Requires-Dist: requests; extra == "dev"
Requires-Dist: setuptools; extra == "dev"
Requires-Dist: twine; extra == "dev"
Requires-Dist: wheel; extra == "dev"
